pit30m/__init__.py
pit30m/all_logs.txt
pit30m/camera.py
pit30m/cli.py
pit30m/data/__init__.py
pit30m/data/log_reader.py
pit30m/data/partitions.py
pit30m/data/submap.py
pit30m/data/submap_utm.pkl
pit30m/fs_util.py
pit30m/indexing.hh
pit30m/indexing.py
pit30m/monkeywrench.py
pit30m/time_utils.py
pit30m/torch/dataset.py
pit30m/torch/dataset_test.py
pit30m/util.py
pit30m-0.0.2.dist-info/LICENSE
pit30m-0.0.2.dist-info/METADATA
pit30m-0.0.2.dist-info/WHEEL
pit30m-0.0.2.dist-info/RECORD
