Metadata-Version: 2.1
Name: pit30m
Version: 0.0.2
Summary: Development kit for the Pit30M large scale localization dataset
Home-page: https://github.com/pit30m/pit30m
License: MIT
Author: Andrei Bârsan
Requires-Python: >=3.9,<4.0
Classifier: Framework :: Robot Framework :: Library
Classifier: Framework :: Robot Framework :: Tool
Classifier: Intended Audience :: Developers
Classifier: Intended Audience :: Education
Classifier: Intended Audience :: Science/Research
Classifier: License :: OSI Approved :: MIT License
Classifier: Operating System :: OS Independent
Classifier: Programming Language :: Python :: 3
Classifier: Programming Language :: Python :: 3.9
Classifier: Programming Language :: Python :: 3.10
Classifier: Programming Language :: Python :: 3.11
Classifier: Topic :: Scientific/Engineering
Classifier: Topic :: Scientific/Engineering :: Artificial Intelligence
Classifier: Topic :: Scientific/Engineering :: Mathematics
Classifier: Topic :: Software Development
Classifier: Topic :: Software Development :: Libraries
Classifier: Topic :: Software Development :: Libraries :: Python Modules
Requires-Dist: fire (>=0.5)
Requires-Dist: fsspec (>=2022)
Requires-Dist: geopandas (>=0.10)
Requires-Dist: joblib
Requires-Dist: lz4 (>=4)
Requires-Dist: matplotlib (>=3.4)
Requires-Dist: numpy (>=1.20)
Requires-Dist: pillow (>=9)
Requires-Dist: pygeos (>=0.12)
Requires-Dist: pyyaml (>=5)
Requires-Dist: s3fs
Requires-Dist: tqdm (>=4)
Requires-Dist: utm (>=0.7.0)
